[
  {
    "Games": 52,
    "wins": 37,
    "Loses": 14,
    "Draw": 1,
    "Season": "22/23",
    "sRating": "8.7"
  },
  {
    "Games": 52,
    "wins": 33,
    "Loses": 18,
    "Draw": 1,
    "Season": "21/22",
    "sRating": "7.5"
  },
  {
    "Games": 51,
    "wins": 34,
    "Loses": 16,
    "Draw": 1,
    "Season": "20/21",
    "sRating": "8.0"
  },
  {
    "Games": 50,
    "wins": 33,
    "Loses": 17,
    "Draw": 1,
    "Season": "19/20",
    "sRating": "7.9"
  }
]
